vgis_infer/__init__.py
vgis_infer/utils.py
vgis_infer/vgisPredictor.py
vgis_infer-1.0.4.dist-info/METADATA
vgis_infer-1.0.4.dist-info/WHEEL
vgis_infer-1.0.4.dist-info/top_level.txt
vgis_infer-1.0.4.dist-info/RECORD
