Metadata-Version: 2.1
Name: vgis_infer
Version: 1.0.4
Summary: A libary for vgis ai inference
Home-page: https://github.com/gisfanmachel/vgisInfer
Author: gisfanmachel
Author-email: gisfanmachel@gmail.com
Keywords: utils,setuptools,development
Classifier: Development Status :: 3 - Alpha
Classifier: Intended Audience :: Developers
Classifier: Topic :: Software Development :: Build Tools
Classifier: License :: OSI Approved :: MIT License
Classifier: Programming Language :: Python :: 3
Classifier: Programming Language :: Python :: 3.7
Classifier: Programming Language :: Python :: 3.8
Classifier: Programming Language :: Python :: 3.9
Classifier: Programming Language :: Python :: 3.10
Classifier: Programming Language :: Python :: 3 :: Only
Requires-Python: >=3.7, <4
Requires-Dist: requests
Requires-Dist: toollib
Requires-Dist: Pillow
Requires-Dist: opencv-python
Requires-Dist: vgis_gis
